azure/mgmt/elastic/__init__.py
azure/mgmt/elastic/_configuration.py
azure/mgmt/elastic/_microsoft_elastic.py
azure/mgmt/elastic/_patch.py
azure/mgmt/elastic/_version.py
azure/mgmt/elastic/py.typed
azure/mgmt/elastic/_utils/__init__.py
azure/mgmt/elastic/_utils/serialization.py
azure/mgmt/elastic/aio/__init__.py
azure/mgmt/elastic/aio/_configuration.py
azure/mgmt/elastic/aio/_microsoft_elastic.py
azure/mgmt/elastic/aio/_patch.py
azure/mgmt/elastic/aio/operations/__init__.py
azure/mgmt/elastic/aio/operations/_all_traffic_filters_operations.py
azure/mgmt/elastic/aio/operations/_associate_traffic_filter_operations.py
azure/mgmt/elastic/aio/operations/_billing_info_operations.py
azure/mgmt/elastic/aio/operations/_connected_partner_resources_operations.py
azure/mgmt/elastic/aio/operations/_create_and_associate_ip_filter_operations.py
azure/mgmt/elastic/aio/operations/_create_and_associate_pl_filter_operations.py
azure/mgmt/elastic/aio/operations/_deployment_info_operations.py
azure/mgmt/elastic/aio/operations/_detach_and_delete_traffic_filter_operations.py
azure/mgmt/elastic/aio/operations/_detach_traffic_filter_operations.py
azure/mgmt/elastic/aio/operations/_elastic_versions_operations.py
azure/mgmt/elastic/aio/operations/_external_user_operations.py
azure/mgmt/elastic/aio/operations/_list_associated_traffic_filters_operations.py
azure/mgmt/elastic/aio/operations/_monitor_operations.py
azure/mgmt/elastic/aio/operations/_monitored_resources_operations.py
azure/mgmt/elastic/aio/operations/_monitored_subscriptions_operations.py
azure/mgmt/elastic/aio/operations/_monitors_operations.py
azure/mgmt/elastic/aio/operations/_open_ai_operations.py
azure/mgmt/elastic/aio/operations/_operations.py
azure/mgmt/elastic/aio/operations/_organizations_operations.py
azure/mgmt/elastic/aio/operations/_patch.py
azure/mgmt/elastic/aio/operations/_tag_rules_operations.py
azure/mgmt/elastic/aio/operations/_traffic_filters_operations.py
azure_mgmt_elastic-2.0.0.dist-info/licenses/LICENSE
azure_mgmt_elastic-2.0.0.dist-info/METADATA
azure_mgmt_elastic-2.0.0.dist-info/WHEEL
azure_mgmt_elastic-2.0.0.dist-info/top_level.txt
azure_mgmt_elastic-2.0.0.dist-info/RECORD
